pytest_minecraft.py
pytest_minecraft-0.2.0.dist-info/entry_points.txt
pytest_minecraft-0.2.0.dist-info/LICENSE
pytest_minecraft-0.2.0.dist-info/WHEEL
pytest_minecraft-0.2.0.dist-info/METADATA
pytest_minecraft-0.2.0.dist-info/RECORD
