Metadata-Version: 2.1
Name: pytest-minecraft
Version: 0.2.0
Summary: A pytest plugin for running tests against Minecraft releases
Home-page: https://github.com/vberlier/pytest-minecraft
License: MIT
Keywords: pytest-plugin,minecraft,datapack,resourcepack,testing
Author: Valentin Berlier
Author-email: berlier.v@gmail.com
Requires-Python: >=3.8,<4.0
Classifier: Framework :: Pytest
Classifier: License :: OSI Approved :: MIT License
Classifier: Programming Language :: Python :: 3
Classifier: Programming Language :: Python :: 3.10
Classifier: Programming Language :: Python :: 3.8
Classifier: Programming Language :: Python :: 3.9
Requires-Dist: pytest (>=6.0.1)
Requires-Dist: requests (>=2.24.0)
Project-URL: Documentation, https://github.com/vberlier/pytest-minecraft
Project-URL: Repository, https://github.com/vberlier/pytest-minecraft
